drsai/__init__.py
drsai/dr_sai.py
drsai/version.py
drsai/backend/__init__.py
drsai/backend/app_worker.py
drsai/backend/run.py
drsai/backend/owebui_pipeline/__init__.py
drsai/backend/owebui_pipeline/api.py
drsai/backend/owebui_pipeline/pipelines/__init__.py
drsai/backend/owebui_pipeline/pipelines/config.py
drsai/backend/owebui_pipeline/pipelines/main.py
drsai/backend/owebui_pipeline/pipelines/schemas.py
drsai/backend/owebui_pipeline/pipelines/blueprints/__init__.py
drsai/backend/owebui_pipeline/pipelines/blueprints/function_calling_blueprint.py
drsai/backend/owebui_pipeline/pipelines/pipelines/drsai_pipeline.py
drsai/backend/owebui_pipeline/pipelines/pipelines/drsai_pipeline/valves.json
drsai/backend/owebui_pipeline/pipelines/utils/__init__.py
drsai/backend/owebui_pipeline/pipelines/utils/pipelines/__init__.py
drsai/backend/owebui_pipeline/pipelines/utils/pipelines/auth.py
drsai/backend/owebui_pipeline/pipelines/utils/pipelines/main.py
drsai/backend/owebui_pipeline/pipelines/utils/pipelines/misc.py
drsai/configs/__init__.py
drsai/configs/constant.py
drsai/modules/__init__.py
drsai/modules/agents/__init__.py
drsai/modules/agents/drsai_remote_agent.py
drsai/modules/agents/drsai_worker_agent.py
drsai/modules/baseagent/__init__.py
drsai/modules/baseagent/drsaiagent.py
drsai/modules/baseagent/long_tool_agent.py
drsai/modules/baseagent/tool_reply_functions.py
drsai/modules/baseagent/user_proxy.py
drsai/modules/components/__init__.py
drsai/modules/components/groupchat_running/__init__.py
drsai/modules/components/groupchat_running/base_running_deamon.py
drsai/modules/components/learning/__init__.py
drsai/modules/components/learning/base_learning_component.py
drsai/modules/components/memory/__init__.py
drsai/modules/components/memory/ragflow_memory.py
drsai/modules/components/model_client/LLMClient.py
drsai/modules/components/model_client/__init__.py
drsai/modules/components/model_context/__init__.py
drsai/modules/components/model_context/drsai_model_context.py
drsai-1.0.5.dist-info/METADATA
drsai-1.0.5.dist-info/WHEEL
drsai-1.0.5.dist-info/RECORD
